Workbook

Sheet Start here
A1: Job tracker for trades
A3: How to use it
A4: 1. Go to the Jobs tab. Add one row for every enquiry, quote and job.
A5: 2. Pick a status from the drop-down: Lead, Quoted, Won, Scheduled, Done, Paid or Lost.
A6: 3. Fill the yellow cells. Profit, balance and the follow-up warning work out for you.
A7: 4. Quotes with a follow-up date in the past turn red, so no quote goes quiet.
A8: 5. The Summary tab shows how many jobs and how much money sit in each status.
A10: Your settings
A11: Your labor cost per hour ($) | B11: 35
A12: What it means: the real cost to you of one hour of work, wages plus taxes. It is used to work out profit on each job.
A14: Yellow cells are for you to fill in. Everything else calculates. Row 2 on the Jobs tab is an example you can delete.

Sheet Jobs
A1: Job # | B1: Date | C1: Customer | D1: Phone | E1: Job type | F1: Status | G1: Quote $ | H1: Materials $ | I1: Labor hours | J1: Labor cost $ | K1: Profit $ | L1: Deposit paid $ | M1: Paid in full $ | N1: Balance $ | O1: Follow-up date | P1: Notes
A2: 1001 | B2: 46307 | C2: Example: Maria Lopez | D2: 555-0100 | E2: Water heater swap | F2: Quoted | G2: 1850 | H2: 980 | I2: 6 | J2: =IF(I2="","",I2*'Start here'!$B$11) -> 210 | K2: =IF(G2="","",G2-N(H2)-N(J2)) -> 660 | N2: =IF(G2="","",G2-N(L2)-N(M2)) -> 1850 | O2: 46327 | P2: Sent quote Tuesday. Call Friday.
J3: =IF(I3="","",I3*'Start here'!$B$11) | K3: =IF(G3="","",G3-N(H3)-N(J3)) | N3: =IF(G3="","",G3-N(L3)-N(M3))
J4: =IF(I4="","",I4*'Start here'!$B$11) | K4: =IF(G4="","",G4-N(H4)-N(J4)) | N4: =IF(G4="","",G4-N(L4)-N(M4))
J5: =IF(I5="","",I5*'Start here'!$B$11) | K5: =IF(G5="","",G5-N(H5)-N(J5)) | N5: =IF(G5="","",G5-N(L5)-N(M5))
J6: =IF(I6="","",I6*'Start here'!$B$11) | K6: =IF(G6="","",G6-N(H6)-N(J6)) | N6: =IF(G6="","",G6-N(L6)-N(M6))
J7: =IF(I7="","",I7*'Start here'!$B$11) | K7: =IF(G7="","",G7-N(H7)-N(J7)) | N7: =IF(G7="","",G7-N(L7)-N(M7))
J8: =IF(I8="","",I8*'Start here'!$B$11) | K8: =IF(G8="","",G8-N(H8)-N(J8)) | N8: =IF(G8="","",G8-N(L8)-N(M8))
J9: =IF(I9="","",I9*'Start here'!$B$11) | K9: =IF(G9="","",G9-N(H9)-N(J9)) | N9: =IF(G9="","",G9-N(L9)-N(M9))
J10: =IF(I10="","",I10*'Start here'!$B$11) | K10: =IF(G10="","",G10-N(H10)-N(J10)) | N10: =IF(G10="","",G10-N(L10)-N(M10))
J11: =IF(I11="","",I11*'Start here'!$B$11) | K11: =IF(G11="","",G11-N(H11)-N(J11)) | N11: =IF(G11="","",G11-N(L11)-N(M11))
J12: =IF(I12="","",I12*'Start here'!$B$11) | K12: =IF(G12="","",G12-N(H12)-N(J12)) | N12: =IF(G12="","",G12-N(L12)-N(M12))
J13: =IF(I13="","",I13*'Start here'!$B$11) | K13: =IF(G13="","",G13-N(H13)-N(J13)) | N13: =IF(G13="","",G13-N(L13)-N(M13))
J14: =IF(I14="","",I14*'Start here'!$B$11) | K14: =IF(G14="","",G14-N(H14)-N(J14)) | N14: =IF(G14="","",G14-N(L14)-N(M14))
... J301: =IF(I301="","",I301*'Start here'!$B$11) | K301: =IF(G301="","",G301-N(H301)-N(J301)) | N301: =IF(G301="","",G301-N(L301)-N(M301))

Sheet Summary
A1: Summary
A3: Status | B3: Jobs | C3: Quote value $
A4: Lead | B4: =COUNTIF(Jobs!$F$2:$F$301,A4) -> 0 | C4: =SUMIF(Jobs!$F$2:$F$301,A4,Jobs!$G$2:$G$301) -> 0
A5: Quoted | B5: =COUNTIF(Jobs!$F$2:$F$301,A5) -> 1 | C5: =SUMIF(Jobs!$F$2:$F$301,A5,Jobs!$G$2:$G$301) -> 1850
A6: Won | B6: =COUNTIF(Jobs!$F$2:$F$301,A6) -> 0 | C6: =SUMIF(Jobs!$F$2:$F$301,A6,Jobs!$G$2:$G$301) -> 0
A7: Scheduled | B7: =COUNTIF(Jobs!$F$2:$F$301,A7) -> 0 | C7: =SUMIF(Jobs!$F$2:$F$301,A7,Jobs!$G$2:$G$301) -> 0
A8: Done | B8: =COUNTIF(Jobs!$F$2:$F$301,A8) -> 0 | C8: =SUMIF(Jobs!$F$2:$F$301,A8,Jobs!$G$2:$G$301) -> 0
A9: Paid | B9: =COUNTIF(Jobs!$F$2:$F$301,A9) -> 0 | C9: =SUMIF(Jobs!$F$2:$F$301,A9,Jobs!$G$2:$G$301) -> 0
A10: Lost | B10: =COUNTIF(Jobs!$F$2:$F$301,A10) -> 0 | C10: =SUMIF(Jobs!$F$2:$F$301,A10,Jobs!$G$2:$G$301) -> 0
A12: Total | B12: =SUM(B4:B10) -> 1 | C12: =SUM(C4:C10) -> 1850
A14: Money numbers
A15: Profit on jobs marked Done or Paid | B15: =SUMIFS(Jobs!$K$2:$K$301,Jobs!$F$2:$F$301,"Done")+SUMIFS(Jobs!$K$2:$K$301,Jobs!$F$2:$F$301,"Paid") -> 0
A16: Still owed on Done jobs | B16: =SUMIFS(Jobs!$N$2:$N$301,Jobs!$F$2:$F$301,"Done") -> 0
A17: Quotes waiting for an answer | B17: =COUNTIF(Jobs!$F$2:$F$301,"Quoted") -> 1
A18: Win rate (won, scheduled, done or paid, out of all quoted and decided) | B18: =IFERROR((B6+B7+B8+B9)/(B5+B6+B7+B8+B9+B10),"") -> 0
